CHANGELOG.txt
License.txt
MANIFEST.in
README.md
setup.py
crakagecalculation/init.py
crakagecalculation.egg-info/PKG-INFO
crakagecalculation.egg-info/SOURCES.txt
crakagecalculation.egg-info/dependency_links.txt
crakagecalculation.egg-info/top_level.txt