Metadata-Version: 2.1
Name: crakagecalculation
Version: 0.1.0
Summary: A simple calculation for the crakage application
Home-page: UNKNOWN
Author: naagabarani
Author-email: naagabarani9302@gmail.com
License: UNKNOWN
Keywords: crakage
Platform: UNKNOWN
Classifier: Development Status :: 3 - Alpha
Classifier: Programming Language :: Python :: 3
Classifier: License :: OSI Approved :: MIT License
Classifier: Operating System :: OS Independent
Requires-Python: >=3.6
